ghostai/__init__.py
ghostai/main.py
ghostai-1.3.1.dist-info/METADATA
ghostai-1.3.1.dist-info/WHEEL
ghostai-1.3.1.dist-info/top_level.txt
ghostai-1.3.1.dist-info/RECORD
